atlaslb/__init__.py
atlaslb/algorithms/leastconnectionlb.py
atlaslb/algorithms/leastconnectionpoweroftwolb.py
atlaslb/algorithms/leastlatencylb.py
atlaslb/algorithms/leastlatencypoweroftwolb.py
atlaslb/algorithms/prequal.py
atlaslb/algorithms/randomlb.py
atlaslb/algorithms/roundrobinlb.py
atlaslb/algorithms/weightedroundrobinlb.py
atlaslb/common/baselb.py
atlaslb/common/loadbalancerfactory.py
atlaslb/common/originserver.py
atlaslb-1.0.3.dist-info/LICENSE
atlaslb-1.0.3.dist-info/METADATA
atlaslb-1.0.3.dist-info/WHEEL
atlaslb-1.0.3.dist-info/top_level.txt
atlaslb-1.0.3.dist-info/RECORD
