Metadata-Version: 2.1
Name: atlaslb
Version: 1.0.3
Summary: Atlas - A reverse proxy software load balancer for Django apps.
Author-email: Pranshu Gupta <pranshug258@outlook.com>
License: MIT License
Project-URL: Homepage, https://pranshug.com/atlas/
Keywords: load balancer,slb,reverse proxy,django
Classifier: License :: OSI Approved :: MIT License
Classifier: Programming Language :: Python
Classifier: Programming Language :: Python :: 3
Requires-Python: >=3.10
License-File: LICENSE
Requires-Dist: Django>=3.0
Requires-Dist: aiohttp
Provides-Extra: dev
